helixtrajectory-0.1.0.data/purelib/cli.py
helixtrajectory-0.1.0.data/purelib/app/__init__.py
helixtrajectory-0.1.0.data/purelib/app/__main__.py
helixtrajectory-0.1.0.data/purelib/app/app.py
helixtrajectory-0.1.0.data/purelib/app/trajectory_generator.py
helixtrajectory-0.1.0.data/purelib/app/trajectory_util.py
helixtrajectory-0.1.0.data/purelib/app/drive/__init__.py
helixtrajectory-0.1.0.data/purelib/app/drive/swerve_drive.py
helixtrajectory-0.1.0.dist-info/LICENSE
helixtrajectory-0.1.0.dist-info/METADATA
helixtrajectory-0.1.0.dist-info/WHEEL
helixtrajectory-0.1.0.dist-info/entry_points.txt
helixtrajectory-0.1.0.dist-info/top_level.txt
helixtrajectory-0.1.0.dist-info/RECORD
